jarvis_cli/__init__.py
jarvis_cli/admin.py
jarvis_cli/config.py
jarvis_cli/exceptions.py
jarvis_cli/file_helper.py
jarvis_cli/formatting.py
jarvis_cli/client/__init__.py
jarvis_cli/client/common.py
jarvis_cli/client/log_entry.py
jarvis_cli/commands/__init__.py
jarvis_cli/commands/action_admin.py
jarvis_cli/commands/action_edit.py
jarvis_cli/commands/action_list.py
jarvis_cli/commands/action_new.py
jarvis_cli/commands/action_show.py
jarvis_cli/interactive/__init__.py
jarvis_cli/interactive/for_events.py
jarvis_cli/interactive/for_init.py
jarvis_cli-0.19.0.dist-info/DESCRIPTION.rst
jarvis_cli-0.19.0.dist-info/METADATA
jarvis_cli-0.19.0.dist-info/RECORD
jarvis_cli-0.19.0.dist-info/WHEEL
jarvis_cli-0.19.0.dist-info/entry_points.txt
jarvis_cli-0.19.0.dist-info/metadata.json
jarvis_cli-0.19.0.dist-info/top_level.txt
