Metadata-Version: 2.0
Name: jarvis-cli
Version: 0.19.0
Summary: Jarvis Python command-line tool
Home-page: https://clb6.github.io/
Author: Michael Hwang
Author-email: hirehwang@gmail.com
License: Apache 2.0
Platform: UNKNOWN
Requires-Dist: click (<7.0)
Requires-Dist: dateparser (<1.0.0)
Requires-Dist: requests
Requires-Dist: tabulate
Requires-Dist: validators (<1.0.0)
